{"add-users.md":"f8ba72ba","halo-integration-setup.md":"88bc1610","index.md":"f2f4a8f7","faq.md":"b58e419a","getting-started.md":"77eeb39a","troubleshooting.md":"3e2ed566","windows-sandbox.md":"420f9908","recommended-deployments.md":"bf148213","connectwise-automate-integration-setup.md":"8e02436d","connectwise-control-integration-setup.md":"71f4a6e4","immy-commands.md":"3f95c339","markdown-examples.md":"00357284","user-roles.md":"83b890f7","azure-graph-permissions-setup.md":"3fed08cf","connectwise-manage-integration-setup.md":"58b19d56","onboarding.md":"aa130f5b","terminology.md":"6f0b1828","ncentral-integration-setup.md":"3ada0ca9","build-your-own-integration.md":"b4fea51b","readme.md":"438fc68f","scripts.md":"7cb2a745","releases.md":"425e7099"}
